{"P1": {"labels": ["documentation"], "postTitle": "Windows\u4e0b\u4f7f\u7528ssh\u8fde\u63a5\u5de5\u5177\u8fde\u63a5docker\u4e2d\u7684centos", "postUrl": "post/Windows-xia-shi-yong-ssh-lian-jie-gong-ju-lian-jie-docker-zhong-de-centos.html", "createdDate": "2025-03-16", "dateLabelColor": "#0969da"}, "labelColorDict": {"bug": "#d73a4a", "documentation": "#0075ca", "duplicate": "#cfd3d7", "enhancement": "#a2eeef", "good first issue": "#7057ff", "help wanted": "#008672", "invalid": "#e4e669", "question": "#d876e3", "wontfix": "#ffffff"}}